setup.cfg
setup.py
rohypnol/__init__.py
rohypnol/models.py
rohypnol/register.py
rohypnol/tests.py
rohypnol.egg-info/PKG-INFO
rohypnol.egg-info/SOURCES.txt
rohypnol.egg-info/dependency_links.txt
rohypnol.egg-info/top_level.txt