Metadata-Version: 1.1
Name: rohypnol
Version: 0.1
Summary: Simplified cache deletion
Home-page: https://github.com/GermanoGuerrini/django-rohypnol
Author: Germano Guerrini
Author-email: germano.guerrini@gmail.com
License: UNKNOWN
Platform: UNKNOWN
Classifier: Development Status :: 5 - Production/Stable
Classifier: Environment :: Web Environment
Classifier: Framework :: Django
Classifier: Intended Audience :: Developers
Classifier: License :: OSI Approved :: MIT License
Classifier: Operating System :: OS Independent
Classifier: Programming Language :: Python
Classifier: Topic :: Utilities
